apifiny/__init__.py
apifiny/__version__.py
apifiny/ac_websocket.py
apifiny/rest_api.py
apifiny/rest_market.py
apifiny/lib/__init__.py
apifiny/lib/apifiny_urls.py
apifiny/lib/utils.py
apifiny/lib/venue_list.py
apifiny-1.2.1.dist-info/LICENSE
apifiny-1.2.1.dist-info/METADATA
apifiny-1.2.1.dist-info/WHEEL
apifiny-1.2.1.dist-info/top_level.txt
apifiny-1.2.1.dist-info/RECORD
